visiontrack/__init__.py
visiontrack/types.py
visiontrack/detection/__init__ .py
visiontrack/detection/base.py
visiontrack/detection/opencv_face.py
visiontrack/examples/webcam_face.py
visiontrack/pipeline/__init__.py
visiontrack/pipeline/face_pipeline.py
visiontrack/recognition/__init__.py
visiontrack/recognition/base.py
visiontrack/tracking/__init__.py
visiontrack/tracking/base.py
visiontrack-0.1.0.dist-info/METADATA
visiontrack-0.1.0.dist-info/WHEEL
visiontrack-0.1.0.dist-info/top_level.txt
visiontrack-0.1.0.dist-info/RECORD
