Metadata-Version: 2.4
Name: visiontrack
Version: 0.1.0
Summary: Modulaire face detection, recognition en tracking library
Author: Jaron
Requires-Python: >=3.9
Requires-Dist: opencv-python
Requires-Dist: numpy
